treem/__init__.py
treem/cli.py
treem/io.py
treem/morph.py
treem/tree.py
treem/commands/__init__.py
treem/commands/check.py
treem/commands/convert.py
treem/commands/find.py
treem/commands/measure.py
treem/commands/modify.py
treem/commands/render.py
treem/commands/repair.py
treem/commands/view.py
treem/utils/__init__.py
treem/utils/geom.py
treem/utils/plot.py
treem-1.1.2.dist-info/METADATA
treem-1.1.2.dist-info/WHEEL
treem-1.1.2.dist-info/entry_points.txt
treem-1.1.2.dist-info/licenses/LICENSE
treem-1.1.2.dist-info/RECORD
