Metadata-Version: 2.4
Name: treem
Version: 1.1.2
Summary: Tree-like morphology data processing tool
Project-URL: Homepage, https://github.com/a1eko/treem
Author-email: Alexander Kozlov <akozlov@kth.se>
License-Expression: MIT
License-File: LICENSE
Keywords: modification,morphology,morphometry,neuron,processing,reconstruction,repair
Classifier: Development Status :: 3 - Alpha
Classifier: License :: OSI Approved :: MIT License
Classifier: Operating System :: OS Independent
Classifier: Programming Language :: Python :: 3
Requires-Python: <4.0,>=3.7
Requires-Dist: matplotlib
Requires-Dist: numpy
Provides-Extra: test
Requires-Dist: flake8; extra == 'test'
Requires-Dist: matplotlib; extra == 'test'
Requires-Dist: numpy; extra == 'test'
Requires-Dist: pytest; extra == 'test'
Requires-Dist: pytest-cov; extra == 'test'
